memoria/__about__.py
memoria/__init__.py
memoria/db_clients.py
memoria/downloader.py
memoria/elasticsearch.py
memoria/env.py
memoria/html.py
memoria/settings.py
memoria/util.py
memoria/logic/__init__.py
memoria/logic/allowlist.py
memoria/logic/history.py
memoria/logic/preview.py
memoria/logic/search.py
memoria/model/__init__.py
memoria/model/allowlist.py
memoria/model/history.py
memoria/model/history_db.py
memoria/model/imported_history.py
memoria/model/page.py
memoria/model/search_result.py
memoria/model/orm/__init__.py
memoria/model/orm/allowlist.py
memoria/model/orm/history.py
memoria/model/orm/page.py
memoria/plugins/__init__.py
memoria/plugins/_allowlist_manager.py
memoria/plugins/_ipv6_regex.py
memoria/plugins/_plugin_suite.py
memoria/plugins/_processing_manager.py
memoria/plugins/allowlist.py
memoria/plugins/processing.py
memoria/plugins/builtin/__init__.py
memoria/plugins/builtin/aiohttp_downloader.py
memoria/plugins/builtin/html_content_finder.py
memoria/plugins/builtin/html_extractor.py
memoria/plugins/builtin/prefix_allowlistrule.py
memoria/plugins/builtin/regex_allowlistrule.py
memoria/web/__init__.py
memoria/web/__main__.py
memoria/web/db_dependencies.py
memoria/web/dependencies.py
memoria/web/lifecycle.py
memoria/web/routes/__init__.py
memoria/web/routes/about.py
memoria/web/routes/history.py
memoria/web/routes/index.py
memoria/web/routes/settings.py
memoria/web/routes/api/__init__.py
memoria/web/routes/api/allowlist.py
memoria/web/routes/api/allowlist_rules.py
memoria/web/routes/api/denylist.py
memoria/web/routes/api/history.py
memoria/web/routes/api/search.py
memoria/web/routes/api/upload_db.py
memoria/web/www/static/logo.png
memoria/web/www/static/oval.svg
memoria/web/www/static/splash.png
memoria/web/www/static/styles.scss
memoria/web/www/static/icons/clock.svg
memoria/web/www/static/icons/delete.svg
memoria/web/www/static/icons/doc-add.svg
memoria/web/www/static/icons/filter.svg
memoria/web/www/static/icons/info.svg
memoria_search-0.2.dist-info/METADATA
memoria_search-0.2.dist-info/WHEEL
memoria_search-0.2.dist-info/entry_points.txt
memoria_search-0.2.dist-info/licenses/LICENSE
memoria_search-0.2.dist-info/RECORD
