Metadata-Version: 2.3
Name: memoria-search
Version: 0.2
Summary: A selfhosted service for indexing and searching personal web history.
Project-URL: Repository, https://github.com/Sidneys1/Memoria
Project-URL: Bug Tracker, https://github.com/Sidneys1/Memoria/issues
Author-email: Sidneys1 <sidneys1@proton.me>
License-File: LICENSE
Classifier: Development Status :: 3 - Alpha
Classifier: License :: OSI Approved :: GNU General Public License v3 (GPLv3)
Classifier: Operating System :: OS Independent
Classifier: Programming Language :: Python :: 3
Classifier: Topic :: Internet :: WWW/HTTP :: Indexing/Search
Classifier: Typing :: Typed
Requires-Python: >=3.12
Requires-Dist: aiofiles~=23.2.1
Requires-Dist: aiohttp~=3.9.5
Requires-Dist: aiosqlite~=0.20.0
Requires-Dist: beautifulsoup4~=4.12.3
Requires-Dist: elasticsearch[async]~=8.13.1
Requires-Dist: fastapi~=0.111.0
Requires-Dist: fasthx~=0.2403.1
Requires-Dist: humanize~=4.9.0
Requires-Dist: pydantic-settings~=2.2.1
Requires-Dist: python-magic~=0.4.27
Requires-Dist: sqlalchemy[asyncio]~=2.0.30
Provides-Extra: dev
Requires-Dist: fastapi-cli; extra == 'dev'
Requires-Dist: hatch; extra == 'dev'
Requires-Dist: isort; extra == 'dev'
Requires-Dist: mypy; extra == 'dev'
Requires-Dist: types-aiofiles; extra == 'dev'
Requires-Dist: types-beautifulsoup4; extra == 'dev'
Provides-Extra: uvicorn
Requires-Dist: uvicorn; extra == 'uvicorn'
